hvpdb_observe/__init__.py
hvpdb_observe-0.1.0.dist-info/METADATA
hvpdb_observe-0.1.0.dist-info/WHEEL
hvpdb_observe-0.1.0.dist-info/entry_points.txt
hvpdb_observe-0.1.0.dist-info/top_level.txt
hvpdb_observe-0.1.0.dist-info/RECORD
