Metadata-Version: 2.4
Name: hvpdb-observe
Version: 0.1.0
Summary: Observability & Metrics Plugin for HVPDB
Requires-Dist: hvpdb
Dynamic: requires-dist
Dynamic: summary
